README.md
setup.cfg
setup.py
auditing/__init__.py
auditing/core.py
auditing/psycopg2auto.py
auditing.egg-info/PKG-INFO
auditing.egg-info/SOURCES.txt
auditing.egg-info/dependency_links.txt
auditing.egg-info/requires.txt
auditing.egg-info/top_level.txt