Metadata-Version: 2.1
Name: auditing
Version: 0.0.12
Summary: A simple auditing library intended for use with Flask-based applications
Home-page: https://github.com/
Author: Emil Haldrup Eriksen
Author-email: emil.h.eriksen@gmail.com
License: MIT
Platform: UNKNOWN
Classifier: Programming Language :: Python :: 3
